Workbook
Name ACTION: #REF!
Name ACTION: #REF!

Sheet Cover
B2: SYSTEM TEST REPORT DOCUMENT
A4: Project Name | B4: Restaurant Internal Management System | E4: Creator | F4: Phạm Tuấn Anh
A5: Project Code | B5: RIMS | E5: Issue Date | F5: 46228
A6: Document Code | B6: SWP391_G3_SystemTestReport_v1.0 | E6: Version | F6: V1.0
A9: Record of change
A10: Effective Date | B10: Version | C10: Change Item | D10: *A,D,M | E10: Change description | F10: Reference
A11: 46228 | B11: V1 | C11: All test case sheets | D11: A | E11: Initial test case design | F11: SWP_SU26_G3_SRS_v2.0

Sheet Test Cases
D1: TEST CASE LIST
B3: Project Name | D3: =Cover!B4 -> Restaurant Internal Management System
B4: Project Code | D4: =Cover!B5 -> RIMS
B5: Test Environment Setup Description | D5: 1. Server: - Backend: Spring Boot, http://localhost:8080 (base path: /rims) - Frontend: React + Vite, http://localhost:5173 (dev proxy forwards /rims/** and /ws-rims to backend) - WebSocket: STOMP over SockJS at /ws-rims 2. Database: - SQL Server, DB name: RIMS_DB, host: localhost:1433 - Auto-recreated on backend restart (ddl-auto: create) — sample data reseeded each time 3. Web Browser: Chrome (latest), Edge (backup) 4. Stack: Spring Boot 4.0.6 / Java 21 backend, React 19 + TypeScript + Vite frontend, JWT auth, VNPay Sandbox payment 5. Test Accounts (password: 123456): admin / chef / waiter / cashier / customer1 (customer2-6 also available) 6. VNPay Sandbox: - URL: https://sandbox.vnpayment.vn/paymentv2/vpcpay.html - TMN Code: D90AVGT4 - Return URL: http://localhost:8080/rims/cashier/payments/vnpay-callback
B8: No | C8: Function Name | D8: Sheet Name | E8: Description | F8: Pre-Condition
B9: 1 | C9: Booking Flow | D9: Booking Flow TestCase | E9: End-to-end reservation flow: Customer creates/cancels a reservation; Waiter creates/views/cancels reservations via Table Management, with conflict validation before saving as QUEUED. | F9: Customer and Waiter accounts exist; at least one AVAILABLE table exists; system time within business hours.
B10: 2 | C10: Creating Order Flow TestCase | D10: Ordering Flow TestCase | E10: End-to-end order creation: Waiter selects an AVAILABLE or RESERVED table (with reservation warning if applicable), adds dishes, confirms order; system sets table to SERVING; Chef sees the new order in the Kitchen Queue. | F10: Waiter and Chef accounts exist; menu items are available; target table is AVAILABLE or RESERVED (not SERVING).
B11: 3 | C11: Customer Checkout Flow | D11: CCreating Order Flow TestCase | E11: End-to-end checkout flow: Cashier opens a SERVING table's order, optionally applies loyalty points, clicks Checkout; system blocks if any item is PREPARING, auto-closes without invoice if all items are CANCELLED, otherwise locks the order for Cash or VNPay payment. | F11: Cashier account exists; table is SERVING with an active order (no PREPARING items); VNPay sandbox reachable for online payment cases.

Sheet Test Statistics
B1: TEST STATISTICS
B3: Project Name | C3: Restaurant Internal Management System | E3: Creator | H3: Phạm Tuấn Anh
B4: Project Code | C4: RIMS | E4: Reviewer/Approver
B5: Document Code | C5: SWP391_G3_SystemTestReport_v1.0 | E5: Issue Date | H5: 46228
B6: Notes | C6: Release 1 includes 3 modules: Booking Flow,Creating Order Flow, Customer Checkout Flow.
B10: No | C10: Module code | D10: Passed | E10: Failed | F10: Pending | G10: N/A | H10: Number of test cases
B11: 1 | C11: ='Booking Flow TestCase'!B2 -> Booking WorkFlow | D11: ='Booking Flow TestCase'!B6 -> 17 | E11: ='Booking Flow TestCase'!C6 -> 0 | F11: ='Booking Flow TestCase'!D6 -> 0 | G11: ='Booking Flow TestCase'!E6 -> 0 | H11: ='Booking Flow TestCase'!B4 -> 17
B12: 2 | C12: ='Creating Order Flow TestCase'!B2 -> Creating Order Workflow | D12: ='Creating Order Flow TestCase'!B6 -> 13 | E12: ='Creating Order Flow TestCase'!C6 -> 0 | F12: ='Creating Order Flow TestCase'!D6 -> 0 | G12: ='Creating Order Flow TestCase'!E6 -> 0 | H12: ='Creating Order Flow TestCase'!B4 -> 13
B13: 3 | C13: Customer Checkout Flow | D13: ='Customer Checkout Flow TestCase'!B6 -> 19 | E13: ='Customer Checkout Flow TestCase'!C6 -> 0 | F13: ='Customer Checkout Flow TestCase'!D6 -> 0 | G13: ='Customer Checkout Flow TestCase'!E6 -> 0 | H13: ='Customer Checkout Flow TestCase'!B4 -> 19
C14: Sub total | D14: =SUM(D9:D13) -> 49 | E14: =SUM(E9:E13) -> 0 | F14: =SUM(F9:F13) -> 0 | G14: =SUM(G9:G13) -> 0 | H14: =SUM(H9:H13) -> 49
C16: Test coverage | E16: =(D14+E14)*100/(H14-G14) -> 100 | F16: %
C17: Test successful coverage | E17: =D14*100/(H14-G14) -> 100 | F17: %

Sheet Booking Flow TestCase
A2: Workflow | B2: Booking WorkFlow | R2: Passed
A3: Test requirement | B3: Verify that a Customer can create/cancel a table reservation, and a Waiter can view and manage reservations (including walk-in creation), with correct field validation and no double-booking of tables. | R3: Failed
A4: Number of TCs | B4: =SUMPRODUCT(--(LEFT(A12:A33,3)="TC_")) -> 17 | R4: Pending
A5: Testing Round | B5: Passed | C5: Failed | D5: Pending | E5: N/A | R5: N/A
A6: Round 1 | B6: =COUNTIF($F12:$F33,B5) -> 17 | C6: =COUNTIF($F12:$F29,C5) -> 0 | D6: =COUNTIF($F12:$F29,D5) -> 0 | E6: =COUNTIF($F12:$F29,E5) -> 0
A7: Round 2 | B7: =COUNTIF($I12:$I33,B5) -> 17 | C7: =COUNTIF($I12:$I29,C5) -> 0 | D7: =COUNTIF($I12:$I29,D5) -> 0 | E7: =COUNTIF($I12:$I29,E5) -> 0
A8: Round 3 | B8: =COUNTIF($L12:$L33,B5) -> 17 | C8: =COUNTIF($L12:$L29,C5) -> 0 | D8: =COUNTIF($L12:$L29,D5) -> 0 | E8: =COUNTIF($L12:$L29,E5) -> 0
A10: Test Case ID | B10: Test Case Description | C10: Test Case Procedure | D10: Expected Results | E10: Pre-conditions | F10: Round 1 | G10: Test date | H10: Tester | I10: Round 2 | J10: Test date | K10: Tester | L10: Round 3 | M10: Test date | N10: Tester | O10: Note
A11: Scenario A: Customer Creates a Reservation (Happy Path & Required Fields)
A12: TC_BOOK_01 | B12: Customer submits a reservation with fully valid information | C12: 1. Login as Customer. 2. Open Reservation Creation screen. 3. Enter Customer Name, Phone Number. 4. Select Reservation Date, Reservation Time. 5. Select an available Table. 6. Click Save. | D12: Reservation is created successfully; confirmation message is shown; new reservation appears in Active Reservations list. | E12: Customer account exists and is logged in; at least one table is available for the chosen date/time. | F12: Passed | G12: 46228 | H12: Tuấn Anh | I12: Passed | J12: 46229 | K12: Hiền | L12: Passed | M12: 46230 | N12: Tuấn Anh
A13: TC_BOOK_02 | B13: Submit reservation with Customer Name left empty | C13: 1. Open Reservation Creation screen. 2. Leave Customer Name empty, fill the rest validly. 3. Click Save. | D13: System shows a required-field validation message for Customer Name; reservation is NOT created. | E13: Customer is logged in. | F13: Passed | G13: 46228 | H13: Tuấn Anh | I13: Passed | J13: 46229 | K13: Hiền | L13: Passed | M13: 46230 | N13: Tuấn Anh
A14: TC_BOOK_03 | B14: Submit reservation with Phone Number left empty | C14: 1. Open Reservation Creation screen. 2. Leave Phone Number empty, fill the rest validly. 3. Click Save. | D14: System shows a required-field validation message for Phone Number; reservation is NOT created. | E14: Customer is logged in. | F14: Passed | G14: 46228 | H14: Tuấn Anh | I14: Passed | J14: 46229 | K14: Hiền | L14: Passed | M14: 46230 | N14: Tuấn Anh
A15: Scenario B: Schedule & Table Selection
A16: TC_BOOK_04 | B16: Select an available table matching the reservation date/time | C16: 1. Choose Reservation Date and Reservation Time. 2. Open Table Selection. 3. Select a table shown as available with sufficient capacity. 4. Click Save. | D16: Reservation is saved with the selected table and capacity; table is reserved for that time slot. | E16: Customer is logged in; at least one table free for the slot. | F16: Passed | G16: 46228 | H16: Tuấn Anh | I16: Passed | J16: 46229 | K16: Hiền | L16: Passed | M16: 46230 | N16: Tuấn Anh
A17: TC_BOOK_05 | B17: Attempt to select a table that is already reserved for the same date/time | C17: 1. Choose a Reservation Date/Time that already has a confirmed reservation on Table X. 2. Try selecting Table X in Table Selection. | D17: Table X is not selectable / is shown unavailable for that slot; system prevents double-booking. | E17: Table X already has an active reservation at the tested date/time. | F17: Passed | G17: 46228 | H17: Tuấn Anh | I17: Passed | J17: 46229 | K17: Hiền | L17: Passed | M17: 46230 | N17: Tuấn Anh
A18: Scenario C: Optional Note & Cancel Creation
A19: TC_BOOK_06 | B19: Submit reservation with an optional Note filled in | C19: 1. Fill all required fields validly. 2. Enter text into the Note field. 3. Click Save. | D19: Reservation is created successfully and the Note content is saved and viewable on the reservation detail. | E19: Customer is logged in. | F19: Passed | G19: 46228 | H19: Tuấn Anh | I19: Passed | J19: 46229 | K19: Hiền | L19: Passed | M19: 46230 | N19: Tuấn Anh
A20: TC_BOOK_07 | B20: Submit reservation leaving Note blank | C20: 1. Fill all required fields validly. 2. Leave Note empty. 3. Click Save. | D20: Reservation is created successfully (Note is optional, no validation error). | E20: Customer is logged in. | F20: Passed | G20: 46228 | H20: Tuấn Anh | I20: Passed | J20: 46229 | K20: Hiền | L20: Passed | M20: 46230 | N20: Tuấn Anh
A21: TC_BOOK_08 | B21: Cancel reservation creation before saving | C21: 1. Fill in some reservation fields. 2. Click Cancel instead of Save. | D21: No reservation is created; user returns to the previous screen; entered data is discarded. | E21: Customer is logged in. | F21: Passed | G21: 46228 | H21: Tuấn Anh | I21: Passed | J21: 46229 | K21: Hiền | L21: Passed | M21: 46230 | N21: Tuấn Anh
A22: Scenario D: Customer Views & Cancels Reservation
A23: TC_BOOK_09 | B23: Customer views the list of active reservations | C23: 1. Open Reservation Cancellation screen. | D23: All active reservations linked to the logged-in customer are displayed with correct date/time/table status. | E23: Customer has at least one active reservation. | F23: Passed | G23: 46228 | H23: Tuấn Anh | I23: Passed | J23: 46229 | K23: Hiền | L23: Passed | M23: 46230 | N23: Tuấn Anh
A24: TC_BOOK_10 | B24: Customer cancels an eligible reservation | C24: 1. Open Reservation Cancellation screen. 2. Select an eligible reservation. 3. Click Cancel Reservation. 4. Confirm the cancellation. | D24: Reservation status changes to Cancelled; the reserved table is released; reservation is removed from the active list. | E24: Customer has an active reservation in WAITING status (arrival time approaching, table already set to RESERVED). | F24: Passed | G24: 46228 | H24: Tuấn Anh | I24: Passed | J24: 46229 | K24: Hiền | L24: Passed | M24: 46230 | N24: Tuấn Anh
A25: TC_BOOK_11 | B25: Refresh button reloads the reservation list with updated status | C25: 1. Open Reservation Cancellation screen. 2. Have another session update a reservation's status. 3. Click Refresh Button. | D25: The reservation list reloads and reflects the latest status without needing a full page reload. | E25: Customer has at least one reservation whose status changed elsewhere. | F25: Passed | G25: 46228 | H25: Tuấn Anh | I25: Passed | J25: 46229 | K25: Hiền | L25: Passed | M25: 46230 | N25: Tuấn Anh
A26: Scenario E: Waiter Manages Reservation (Walk-in / Front Desk)
A27: TC_BOOK_12 | B27: Waiter views reservation detail for a selected table/date | C27: 1. Login as Waiter. 2. Open Current Reservation Detail screen. 3. Select a table with an existing reservation. | D27: Reservation details (customer name, phone, time, note) for that table are displayed correctly. | E27: Waiter is logged in; selected table has an existing reservation. | F27: Passed | G27: 46228 | H27: Tuấn Anh | I27: Passed | J27: 46229 | K27: Hiền | L27: Passed | M27: 46230 | N27: Tuấn Anh
A28: TC_BOOK_13 | B28: Waiter creates a new reservation directly (walk-in guest) | C28: 1. Open Create Reservation screen (Waiter side). 2. Enter guest info, date/time, and select an available table. 3. Save. | D28: New reservation is created and visible in the reservation list; table availability is updated. | E28: Waiter is logged in; at least one table is free. | F28: Passed | G28: 46228 | H28: Tuấn Anh | I28: Passed | J28: 46229 | K28: Hiền | L28: Passed | M28: 46230 | N28: Tuấn Anh
A29: TC_BOOK_14 | B29: Waiter edits an existing reservation to a new time without conflict | C29: 1. Open Edit Reservation for an existing reservation. 2. Change the reservation time to a slot with no conflict. 3. Save. | D29: Reservation is updated with the new time; no conflict error is shown; table availability is recalculated correctly. | E29: Waiter is logged in; an existing reservation is available to edit; target slot is free. | F29: Passed | G29: 46228 | H29: Tuấn Anh | I29: Passed | J29: 46229 | K29: Hiền | L29: Passed | M29: 46230 | N29: Tuấn Anh
A30: TC_BOOK_15 | B30: Attempt to cancel a reservation that is already Cancelled or Completed | C30: 1. Open a reservation already in Cancelled/Completed status(or call cancel twice on the same reservation). 2. Click Cancel Reservation again. | D30: System rejects with a clear error message (reservation already closed); no duplicate action, no side effects on table status. | E30: An existing reservation already has status Cancelled or Completed. | F30: Passed | G30: 46228 | H30: Tuấn Anh | I30: Passed | J30: 46229 | K30: Hiền | L30: Passed | M30: 46230 | N30: Tuấn Anh
A31: Scenario F: Duplicate Booking Prevention (CustomerId & Phone)
A32: TC_BOOK_16 | B32: Block the creation of a second reservation when the Customer ID is the same but the Phone Number is different. | C32: 1. Log in as Customer A. One reservation is active today with the phone number "0912345678". 2. Open Reservation Creation, create a new reservation for the same day, and enter a different phone number (e.g., "0987654321"). 3. Click Save. | D32: The system refused to create the reservation with a clear message (already booked for the day); the reservation was NOT created even though the phone number entered was different from the previous reservation. | E32: Customer A has one active reservation (WAITING/CONFIRMED) today. | F32: Passed | G32: 46228 | H32: Tuấn Anh | I32: Passed | J32: 46229 | K32: Hiền | L32: Passed | M32: 46230 | N32: Tuấn Anh
A33: TC_BOOK_17 | B33: Block the creation of a second reservation if the Phone Number is the same but the Customer ID is different (or if the Waiter creates a walk-in). | C33: 1. Customer A has an active reservation for today with the phone number "0912345678". 2. Log in as Customer B (a different Customer ID) or as a walk-in waiter, and enter the correct phone number "0912345678" for the new reservation for the same day. 3. Click Save. | D33: The system refused to create the reservation with a clear message; the reservation was NOT created even though the CustomerId associated with the request was different from the CustomerId of the existing reservation. | E33: Customer A has an active reservation today with the phone number "0912345678"; Customer B's account or Waiter privileges are available to create a walk-in. | F33: Passed | G33: 46228 | H33: Tuấn Anh | I33: Passed | J33: 46229 | K33: Hiền | L33: Passed | M33: 46230 | N33: Tuấn Anh

Sheet Creating Order Flow TestCase
A2: Workflow | B2: Creating Order Workflow | R2: Passed
A3: Test requirement | B3: Verify that a Waiter can create and update a table's order, that new/updated items are sent to the Chef's Kitchen Queue in real time, and that the Chef can complete, cancel, and annotate dishes correctly. | R3: Failed
A4: Number of TCs | B4: =SUMPRODUCT(--(LEFT(A12:A28,3)="TC_")) -> 13 | R4: Pending
A5: Testing Round | B5: Passed | C5: Failed | D5: Pending | E5: N/A | R5: N/A
A6: Round 1 | B6: =COUNTIF($F12:$F28,B5) -> 13 | C6: =COUNTIF($F12:$F28,C5) -> 0 | D6: =COUNTIF($F12:$F28,D5) -> 0 | E6: =COUNTIF($F12:$F28,E5) -> 0
A7: Round 2 | B7: =COUNTIF($I12:$I28,B5) -> 13 | C7: =COUNTIF($I12:$I28,C5) -> 0 | D7: =COUNTIF($I12:$I28,D5) -> 0 | E7: =COUNTIF($I12:$I28,E5) -> 0
A8: Round 3 | B8: =COUNTIF($L12:$L28,B5) -> 13 | C8: =COUNTIF($L12:$L28,C5) -> 0 | D8: =COUNTIF($L12:$L28,D5) -> 0 | E8: =COUNTIF($L12:$L28,E5) -> 0
A10: Test Case ID | B10: Test Case Description | C10: Test Case Procedure | D10: Expected Results | E10: Pre-conditions | F10: Round 1 | G10: Test date | H10: Tester | I10: Round 2 | J10: Test date | K10: Tester | L10: Round 3 | M10: Test date | N10: Tester | O10: Note
A11: Scenario A: Waiter Creates a New Order (Happy Path & Validation)
A12: TC_ORD_01 | B12: Create a new order with valid menu items | C12: 1. Select table T09. 2. Add "Há cảo tôm" and "Trà ô long Đài Loan". 3. Click Create Order. | D12: Order is created successfully. Order status becomes SERVING, dish status PREPARING. Table T09 updates status. | E12: Waiter logged in (waiter); Table T09 available. | F12: Passed | G12: 46228 | H12: Vinh | I12: Passed | J12: 46229 | K12: Anh Tuấn | L12: Passed | M12: 46230 | N12: Tuấn Anh
A13: TC_ORD_02 | B13: Search menu items by keyword in Create Order screen | C13: 1. Open Create Order screen. 2. Type keyword "Dimsum" or "Lẩu" in the search bar. | D13: Menu filters correctly (e.g., "Dimsum" displays "Há cảo tôm", "Xíu mại tôm thịt"...; "Lẩu" displays "Lẩu Tứ Xuyên cay tê (Mala)") | E13: Waiter is on Create Order screen; menu items exist in the system. | F13: Passed | G13: 46228 | H13: Vinh | I13: Passed | J13: 46229 | K13: Anh Tuấn | L13: Passed | M13: 46230 | N13: Tuấn Anh
A14: TC_ORD_03 | B14: Filter menu items by category | C14: 1. Open Create Order screen. 2. Select "Dimsum / Điểm tâm" or "Đồ uống" category. | D14: List updates instantly. Selecting "Đồ uống" shows only beverage items ("Trà hoa cúc Trung Hoa", "Bia Tsingtao"...). | E14: Waiter is on Create Order screen; multiple categories exist. | F14: Passed | G14: 46228 | H14: Vinh | I14: Passed | J14: 46229 | K14: Anh Tuấn | L14: Passed | M14: 46230 | N14: Tuấn Anh
A15: TC_ORD_04 | B15: Adjust item quantities using Quantity Controls | C15: 1. Open Create Order screen. 2. Click + button. 3. Click - button. 4. Manually enter 3 in quantity field. | D15: OrdetItem update to 3 quantity field dish. | E15: Waiter is on Create Order screen; Item "Cơm rang Dương Châu" added to cart (Default Qty: 1). | F15: Passed | G15: 46228 | H15: Vinh | I15: Passed | J15: 46229 | K15: Anh Tuấn | L15: Passed | M15: 46230 | N15: Tuấn Anh
A16: TC_ORD_05 | B16: Confirm order creation with an empty cart | C16: 1. Open Create Order screen. 2. Leave cart empty. 3. Click "Tạo Đơn Hàng". | D16: System blocks action and displays error: "Vui lòng chọn ít nhất 1 món." | E16: Waiter is on Create Order screen; Waiter on Create Order screen for table T11. | F16: Passed | G16: 46228 | H16: Vinh | I16: Passed | J16: 46229 | K16: Anh Tuấn | L16: Passed | M16: 46230 | N16: Tuấn Anh
A17: TC_ORD_06 | B17: Order an out-of-stock (Unavailable) item | C17: 1. Open Create Order screen. 2.Waiter navigates to Create Order screen. | D17: Item "Vịt quay Bắc Kinh nguyên con" is grayed out / marked "Out of Stock" and cannot be added to cart. | E17: Waiter is on Create Order screen; "Vịt quay Bắc Kinh nguyên con" marked isAvailable = false. | F17: Passed | G17: 46228 | H17: Vinh | I17: Passed | J17: 46229 | K17: Anh Tuấn | L17: Passed | M17: 46230 | N17: Tuấn Anh
A18: Scenario B: Kitchen Receives & Processes the Order
A19: TC_ORD_07 | B19: Real-time order synchronization to Kitchen Queue | C19: 1. Waiter submits order for table T02 with "Mapo đậu hũ Tứ Xuyên". 2. Observe Chef's Kitchen Queue screen. | D19: Item card "Mapo đậu hũ Tứ Xuyên - Table T02" appears on Chef screen in PREPARING state within realtime without manual refresh. | E19: Waiter and Chef logged in on dual screens. | F19: Passed | G19: 46228 | H19: Vinh | I19: Passed | J19: 46229 | K19: Anh Tuấn | L19: Passed | M19: 46230 | N19: Tuấn Anh
A20: TC_ORD_08 | B20: Search/Filter Kitchen Queue by Table or Order ID | C20: 1. Open Kitchen Queue. 2. Chef enters "T01" in Kitchen Queue search bar. | D20: Queue filters immediately to show only items belonging to table T01. | E20: Active order items present in Kitchen Queue. | F20: Passed | G20: 46228 | H20: Vinh | I20: Passed | J20: 46229 | K20: Anh Tuấn | L20: Passed | M20: 46230 | N20: Tuấn Anh
A21: TC_ORD_09 | B21: Chef marks a dish as Completed | C21: 1. Open Kitchen Queue. 2. Chef clicks Complete Dish on "Gà cung bảo Tứ Xuyên". | D21: Dish status changes from PREPARING to COMPLETED. Item moves out of active cooking queue | E21: Item "Gà cung bảo Tứ Xuyên" for T03 is in PREPARING state. | F21: Passed | G21: 46228 | H21: Vinh | I21: Passed | J21: 46229 | K21: Anh Tuấn | L21: Passed | M21: 46230 | N21: Tuấn Anh
A22: TC_ORD_10 | B22: Chef cancels a dish with mandatory cancellation reason | C22: 1. Open Kitchen Queue. 2. Click Cancel Dish without reason. 3. Enter reason "Out of fresh seafood". 4. Confirm cancellation. | D22: Empty reason is rejected. Valid cancellation updates dish status to CANCELLED and notifies Waiter in real-time. | E22: Item "Lẩu Quảng Đông hải sản - nồi 4 người" is in PREPARING state. | F22: Passed | G22: 46228 | H22: Vinh | I22: Passed | J22: 46229 | K22: Anh Tuấn | L22: Passed | M22: 46230 | N22: Tuấn Anh
A23: TC_ORD_11 | B23: Chef adds internal note for Waiter on preparing dish | C23: 1. Open Preparing Dish Details. 2. Enter note: "Requires 10 more mins due to deep stewing". 3. Click Send Note. | D23: Note is saved and instantly displays under "Bò lúc lắc Quảng Đông" on Waiter Order Details screen. | E23: Item "Bò lúc lắc Quảng Đông" in PREPARING state. | F23: Passed | G23: 46228 | H23: Vinh | I23: Passed | J23: 46229 | K23: Anh Tuấn | L23: Passed | M23: 46230 | N23: Tuấn Anh
A24: Scenario C: Advanced Business Logic & Edge Cases
A25: TC_ORD_12 | B25: Restrict editing completed dishes | C25: 1. Waiter opens Edit Order for table T05. 2. Attempts to delete or decrease qty of "Bánh bao xá xíu nướng". | D25: System disables modifications for COMPLETED items with warning: "Completed items cannot be modified or deleted." | E25: Item "Bánh bao xá xíu nướng" on T05 order is COMPLETED. | F25: Passed | G25: 46228 | H25: Vinh | I25: Passed | J25: 46229 | K25: Anh Tuấn | L25: Passed | M25: 46230 | N25: Tuấn Anh
A26: TC_ORD_13 | B26: Real-time status update on Waiter screen | C26: 1. Chef clicks Complete Dish for "Cá hấp Hồng Kông" (Table T07) | D26: Status on Waiter screen instantly updates to COMPLETED (green highlight) without page reload. | E26: Waiter views Order Details for T07; "Cá hấp Hồng Kông" is PREPARING. | F26: Passed | G26: 46228 | H26: Vinh | I26: Passed | J26: 46229 | K26: Anh Tuấn | L26: Passed | M26: 46230 | N26: Tuấn Anh

Sheet Customer Checkout Flow TestCase
A2: Workflow | B2: Customer Checkout Workflow | R2: Passed
A3: Test requirement | B3: Verify that a Cashier can review an order, look up/register a customer, apply loyalty-point discounts within limits, complete payment via Cash or VNPay, and that a correct invoice/PDF is produced. | R3: Failed
A4: Number of TCs | B4: =SUMPRODUCT(--(LEFT(A12:A35,3)="TC_")) -> 19 | R4: Pending
A5: Testing Round | B5: Passed | C5: Failed | D5: Pending | E5: N/A | R5: N/A
A6: Round 1 | B6: =COUNTIF($F12:$F35,B5) -> 19 | C6: =COUNTIF($F12:$F32,C5) -> 0 | D6: =COUNTIF($F12:$F32,D5) -> 0 | E6: =COUNTIF($F12:$F32,E5) -> 0
A7: Round 2 | B7: =COUNTIF($I12:$I35,B5) -> 19 | C7: =COUNTIF($I12:$I32,C5) -> 0 | D7: =COUNTIF($I12:$I32,D5) -> 0 | E7: =COUNTIF($I12:$I32,E5) -> 0
A8: Round 3 | B8: =COUNTIF($L12:$L35,B5) -> 19 | C8: =COUNTIF($L12:$L32,C5) -> 0 | D8: =COUNTIF($L12:$L32,D5) -> 0 | E8: =COUNTIF($L12:$L32,E5) -> 0
A10: Test Case ID | B10: Test Case Description | C10: Test Case Procedure | D10: Expected Results | E10: Pre-conditions | F10: Round 1 | G10: Test date | H10: Tester | I10: Round 2 | J10: Test date | K10: Tester | L10: Round 3 | M10: Test date | N10: Tester | O10: Note
A11: Scenario A: View Order Details & Find Customer
A12: TC_PAY_01 | B12: Cashier views Order Details for a table ready to checkout (only COMPLETED items shown) | C12: 1. Login as Cashier. 2. Open Table Map. 3. Select a table with a servable order. 4. Open Order Details. | D12: Only OrderItems with status COMPLETED are displayed (PREPARING items do not appear); subtotal/running total is calculated only from these COMPLETED items, with correct 10% VAT. | E12: Cashier logged in; table has a SERVING order with at least 1 COMPLETED item. | F12: Passed | G12: 46228 | H12: nghĩa | I12: Passed | J12: 46229 | K12: Bắc | L12: Passed | M12: 46230 | N12: Tuấn Anh
A13: TC_PAY_02 | B13: Order Details when ALL items are still PREPARING (none COMPLETED yet) | C13: 1. Open Order Details for a table whose order has all items still PREPARING. | D13: Item list displays empty; totalAmountBeforeVat/vatAmount/finalAmount all = 0, no error, no crash. | E13: Order has ≥1 item, all PREPARING. | F13: Passed | G13: 46228 | H13: nghĩa | I13: Passed | J13: 46229 | K13: Bắc | L13: Passed | M13: 46230 | N13: Tuấn Anh
A14: TC_PAY_03 | B14: Cashier searches an existing customer by phone number | C14: 1. Open Customer Loyalty search. 2. Enter a phone number with an existing loyalty account. | D14: A customer with role CUSTOMER and this phone exists. | E14: Entered phone number does not belong to any existing customer. | F14: Passed | G14: 46228 | H14: nghĩa | I14: Passed | J14: 46229 | K14: Bắc | L14: Passed | M14: 46230 | N14: Tuấn Anh
A15: TC_PAY_04 | B15: Cashier searches a phone number with no matching loyalty account | C15: 1. Open Customer Loyalty search. 2. Enter a phone with no account | D15: System shows "Chưa có tài khoản! Đăng ký nhanh" and create New Customer Registration. | E15: Phone doesn't belong to any CUSTOMER-role user. | F15: Passed | G15: 46228 | H15: nghĩa | I15: Passed | J15: 46229 | K15: Bắc | L15: Passed | M15: 46230 | N15: Tuấn Anh
A16: Scenario B: Loyalty Points & New Customer Registration
A17: TC_PAY_05 | B17: Apply a loyalty point redemption within the allowed limit | C17: 1. With a linked customer whose points cover < 50% of the bill, enter a valid redeem amount. 2. Apply. | D17: Discount = pointsUsed × 1,000 VND is subtracted from finalAmount; customer's remaining points are reduced correctly; newly earned points are calculated on the finalAmount AFTER the discount is applied. | E17: Customer has enough points for a valid redemption. | F17: Passed | G17: 46228 | H17: nghĩa | I17: Passed | J17: 46229 | K17: Bắc | L17: Passed | M17: 46230 | N17: Tuấn Anh
A18: TC_PAY_06 | B18: Attempt to redeem points exceeding 50% of the invoice amount | C18: 1. Enter a point amount whose discount > 50% of finalAmount (customer still has enough points). 2. Apply | D18: System does auto-cap to 50%; Cashier cannot input point higher than 50% | E18: Customer's points are large enough to exceed the 50% cap. | F18: Passed | G18: 46228 | H18: nghĩa | I18: Passed | J18: 46229 | K18: Bắc | L18: Passed | M18: 46230 | N18: Tuấn Anh
A19: TC_PAY_07 | B19: Redeem exactly 50% of the invoice (boundary case) | C19: 1. Enter a point amount whose discount = exactly 50% of finalAmount. 2. Apply. | D19: Transaction is accepted(The accuracy must be 50%.) | E19: Customer has enough points for exactly 50%. | F19: Passed | G19: 46228 | H19: nghĩa | I19: Passed | J19: 46229 | K19: Bắc | L19: Passed | M19: 46230 | N19: Tuấn Anh
A20: TC_PAY_08 | B20: Redeem when customer doesn't have enough points | C20: 1. Enter a point amount greater than the customer's current rewardPoints. 2. Apply. | D20: The system automatically limits the points to the customer's current balance (below 50% of the bill); cashiers cannot enter points higher than the current balance. | E20: Customer's points are less than the requested redeem amount. | F20: Passed | G20: 46228 | H20: nghĩa | I20: Passed | J20: 46229 | K20: Bắc | L20: Passed | M20: 46230 | N20: Tuấn Anh
A21: TC_PAY_09 | B21: Register a new customer using the searched phone number | C21: 1. From TC_04's "not found" result, click New Customer Registration. 2. Fill info, Save. | D21: New account created with username=phone, rewardPoints=0, hashed default password, role CUSTOMER, automatically linked to the current invoice. | E21: Phone confirmed to not exist yet. | F21: Passed | G21: 46228 | H21: nghĩa | I21: Passed | J21: 46229 | K21: Bắc | L21: Passed | M21: 46230 | N21: Tuấn Anh
A22: TC_PAY_10 | B22: Register new customer with a phone that already exists (race condition) | C22: 1.Cashier search phone of staff 2.Register with info 3.Save | D22: show message"Lỗi tạo khách hàng. Có thể số điện thoại đã tồn tại!". Cannot register new customer | E22: The phone number already exists in the system. | F22: Passed | G22: 46228 | H22: nghĩa | I22: Passed | J22: 46229 | K22: Bắc | L22: Passed | M22: 46230 | N22: Tuấn Anh
A23: Scenario C: Order Lock & Payment Confirmation (new — not in the original 13 cases)
A24: TC_PAY_11 | B24: Confirm payment while order still has PREPARING items | C24: 1. Cashier clicks "Confirm" (processPayment) for an order with ≥1 PREPARING item. | D24: Show message "Không thể thực hiện thanh toán đơn hàng.Vui lòng huỷ hoặc hoàn thành các món còn lại!". | E24: Order SERVING, has a PREPARING item. | F24: Passed | G24: 46228 | H24: nghĩa | I24: Passed | J24: 46229 | K24: Bắc | L24: Passed | M24: 46230 | N24: Tuấn Anh
A25: TC_PAY_12 | B25: Confirm payment when order has no COMPLETED items at all (everything cancelled) | C25: 1. Cashier clicks "Confirm" for an order where every item is CANCELLED. | D25: Orders are automatically canceled without generating an invoice. | E25: Order SERVING, all items CANCELLED, none COMPLETED. | F25: Passed | G25: 46228 | H25: nghĩa | I25: Passed | J25: 46229 | K25: Bắc | L25: Passed | M25: 46230 | N25: Tuấn Anh
A26: TC_PAY_13 | B26: Cancel the payment process mid-way (unlockOrder) | C26: 1. Order is LOCKED (confirmed but not yet paid). 2. Cashier clicks Cancel/Back on the Payment Method screen. | D26: Order reverts to SERVING; pendingCustomerId, pendingPointsUsed, lockedAt are all cleared; table continues to be served normally, order can still be edited. | E26: Order currently LOCKED. | F26: Passed | G26: 46228 | H26: nghĩa | I26: Passed | J26: 46229 | K26: Bắc | L26: Passed | M26: 46230 | N26: Tuấn Anh
A27: Scenario D: Cash Payment
A28: TC_PAY_14 | B28: Select Cash payment and confirm with sufficient amount | C28: 1. Order already LOCKED. 2. Choose Cash. 3. Enter amountPaid ≥ finalAmount (after any discount). 4. Confirm. | D28: Cash payment successful. A success screen appears and order information is displayed. | E28: Order LOCKED, finalAmount determined. | F28: Passed | G28: 46228 | H28: nghĩa | I28: Passed | J28: 46229 | K28: Bắc | L28: Passed | M28: 46230 | N28: Tuấn Anh
A29: TC_PAY_15 | B29: Confirm blocked when amountPaid < finalAmount | C29: 1. Choose Cash. 2. Enter amountPaid less than finalAmount after subtracting the previewed point discount (previewFinalAmount). | D29: Unable to confirm cash payment. | E29: Order LOCKED. | F29: Passed | G29: 46228 | H29: nghĩa | I29: Passed | J29: 46229 | K29: Bắc | L29: Passed | M29: 46230 | N29: Tuấn Anh
A30: Scenario E: VNPay Online Payment
A31: TC_PAY_16 | B31: Select VNPay and generate payment link successfully | C31: 1. Choose VNPay for an order (LOCKED/SERVING) with ≥1 COMPLETED item. | D31: VNPay link generated with correct amountVND; order transitions to LOCKED | E31: Order has finalAmount > 0 (has COMPLETED item). | F31: Passed | G31: 46228 | H31: nghĩa | I31: Passed | J31: 46229 | K31: Bắc | L31: Passed | M31: 46230 | N31: Tuấn Anh
A32: TC_PAY_17 | B32: VNPay callback success (processVnPaySuccess) | C32: 1. Complete payment on VNPay sandbox. 2. System receives the IPN callback. | D32: Display the successful payment screen for VNPAY/QR code. | E32: VNPay sandbox reachable; order LOCKED awaiting callback. | F32: Passed | G32: 46228 | H32: nghĩa | I32: Passed | J32: 46229 | K32: Bắc | L32: Passed | M32: 46230 | N32: Tuấn Anh
A33: TC_PAY_18 | B33: VNPay callback failed/cancelled (processVnPayFailed) | C33: 1. Cancel the transaction or use a failing test card on VNPay. | D33: Payment failed, displaying the "Payment Fail" screen. | E33: Order LOCKED awaiting callback. | F33: Passed | G33: 46228 | H33: nghĩa | I33: Passed | J33: 46229 | K33: Bắc | L33: Passed | M33: 46230 | N33: Tuấn Anh
A34: Scenario F: Loyalty Points Earn Calculation Detail
A35: TC_PAY_19 | B35: Earned points are calculated on finalAmount AFTER the redemption discount, not the original total | C35: 1. Customer redeems some points in the same invoice (e.g., original bill 1,000,000 VND, redeem 300 points = 300,000 VND discount). 2. Complete payment. | D35: pointsEarned = 1% of (1,000,000 − 300,000) = 1% × 700,000 = 7,000 VND → 7 points (rounded down per 1,000), NOT 1% of the original 1,000,000 (which would be 10 points). | E35: Customer has enough points for a valid redemption in the same transaction. | F35: Passed | G35: 46228 | H35: nghĩa | I35: Passed | J35: 46229 | K35: Bắc | L35: Passed | M35: 46230 | N35: Tuấn Anh
